mir_eval/__init__.py
mir_eval/alignment.py
mir_eval/beat.py
mir_eval/chord.py
mir_eval/display.py
mir_eval/hierarchy.py
mir_eval/io.py
mir_eval/key.py
mir_eval/melody.py
mir_eval/multipitch.py
mir_eval/onset.py
mir_eval/pattern.py
mir_eval/segment.py
mir_eval/separation.py
mir_eval/sonify.py
mir_eval/tempo.py
mir_eval/transcription.py
mir_eval/transcription_velocity.py
mir_eval/util.py
mir_eval-0.8.1.dist-info/LICENSE.txt
mir_eval-0.8.1.dist-info/METADATA
mir_eval-0.8.1.dist-info/WHEEL
mir_eval-0.8.1.dist-info/top_level.txt
mir_eval-0.8.1.dist-info/RECORD
