Metadata-Version: 2.2
Name: mir_eval
Version: 0.8.1
Summary: Common metrics for common audio/music processing tasks.
Home-page: https://github.com/mir-evaluation/mir_eval
Author: Colin Raffel
Author-email: craffel@gmail.com
License: MIT
Classifier: License :: OSI Approved :: MIT License
Classifier: Programming Language :: Python
Classifier: Development Status :: 5 - Production/Stable
Classifier: Intended Audience :: Developers
Classifier: Topic :: Multimedia :: Sound/Audio :: Analysis
Classifier: Programming Language :: Python :: 3
Classifier: Programming Language :: Python :: 3.7
Classifier: Programming Language :: Python :: 3.8
Classifier: Programming Language :: Python :: 3.9
Classifier: Programming Language :: Python :: 3.10
Classifier: Programming Language :: Python :: 3.11
Classifier: Programming Language :: Python :: 3.12
Classifier: Programming Language :: Python :: 3.13
License-File: LICENSE.txt
Requires-Dist: numpy>=1.15.4
Requires-Dist: scipy>=1.4.0
Requires-Dist: decorator
Provides-Extra: display
Requires-Dist: matplotlib>=3.3.0; extra == "display"
Provides-Extra: docs
Requires-Dist: numpydoc; extra == "docs"
Requires-Dist: sphinx_rtd_theme; extra == "docs"
Requires-Dist: matplotlib>=3.3.0; extra == "docs"
Provides-Extra: tests
Requires-Dist: matplotlib>=3.3.0; extra == "tests"
Requires-Dist: pytest; extra == "tests"
Requires-Dist: pytest-cov; extra == "tests"
Requires-Dist: pytest-mpl; extra == "tests"
